judge_qna_handler/__init__.py
judge_qna_handler/handler.py
judge_qna_handler-0.0.3.dist-info/METADATA
judge_qna_handler-0.0.3.dist-info/WHEEL
judge_qna_handler-0.0.3.dist-info/top_level.txt
judge_qna_handler-0.0.3.dist-info/RECORD
