Metadata-Version: 2.1
Name: judge_qna_handler
Version: 0.0.3
Requires-Python: >=3.11
Requires-Dist: flask>=3.0
